frispy/__init__.py
frispy/disc.py
frispy/equations_of_motion.py
frispy/model.py
frispy-2.0.2.dist-info/LICENSE
frispy-2.0.2.dist-info/METADATA
frispy-2.0.2.dist-info/WHEEL
frispy-2.0.2.dist-info/RECORD
