Metadata-Version: 2.1
Name: frispy
Version: 2.0.2
Summary: Frisbee simulation.
Author: Tom McClintock
Author-email: thmsmcclintock@gmail.com
Requires-Python: >=3.9,<4.0
Classifier: Programming Language :: Python :: 3
Classifier: Programming Language :: Python :: 3.9
Classifier: Programming Language :: Python :: 3.10
Classifier: Programming Language :: Python :: 3.11
Requires-Dist: numpy (>=1.23.5,<2.0.0)
Requires-Dist: scipy (>=1.9.3,<2.0.0)
